check_gitlab_scheduler.py
check_gitlab_scheduler-1.0.0.dist-info/LICENSE
check_gitlab_scheduler-1.0.0.dist-info/METADATA
check_gitlab_scheduler-1.0.0.dist-info/WHEEL
check_gitlab_scheduler-1.0.0.dist-info/entry_points.txt
check_gitlab_scheduler-1.0.0.dist-info/RECORD
