Metadata-Version: 2.1
Name: check-gitlab-scheduler
Version: 1.0.0
Summary: Check Gitlab Scheduled Pipelines and its jobs for errors.
Home-page: https://github.com/telekom-mms/check_gitlab_scheduler
License: GPL-3.0-only
Author: Christopher Grau
Requires-Python: >=3.6,<4.0
Classifier: License :: OSI Approved :: GNU General Public License v3 (GPLv3)
Classifier: Programming Language :: Python :: 3
Classifier: Programming Language :: Python :: 3.6
Classifier: Programming Language :: Python :: 3.7
Classifier: Programming Language :: Python :: 3.8
Classifier: Programming Language :: Python :: 3.9
Classifier: Programming Language :: Python :: 3.10
Classifier: Programming Language :: Python :: 3.11
Project-URL: Documentation, https://github.com/telekom-mms/check_gitlab_scheduler
Project-URL: Repository, https://github.com/telekom-mms/check_gitlab_scheduler
